{
    "reportDetails":[
        {
            "custodian":"Kiara Tamm",
            "custodianMessages":[
                {
                    "exchange":"all",
                    "message":"Please excuse the \"dust\" while I work with the Nu  Development Team to finalize the reporting pages.",
                    "pair":"all"
                }
            ],
            "grants":[
                {
                    "custodianFee":36450,
                    "discussionURL":"https://discuss.nubits.com/t/proposal-to-operate-a-nubits-grant-to-provide-early-stage-dual-side-liquidity-and-shareholder-dividends",
                    "dividendYielding":true,
                    "dividendsPaid":[
                        {
                            "amountNBT":50000,
                            "amountPPC":68306,
                            "description":"Period 001A Dividend Distribution",
                            "distributionAddresses":481,
                            "distributionTXID":"b7f3f769ac81322e60e339946d97411f85fca29a8689cb004b625a0e215e1640",
                            "nuBlockHeight":86004,
                            "pricePPCNBT":0.732,
                            "timestamp":1416539478
                        },
                        {
                            "amountNBT":20000,
                            "amountPPC":65547,
                            "description":"Period 001B Dividend Distribution",
                            "distributionAddresses":741,
                            "distributionTXID":"c583c0e26c17644577f2343b95faa07609be40cc7a6d6926f0c648e92743af76",
                            "nuBlockHeight":186947,
                            "pricePPCNBT":0.30512,
                            "timestamp":1421712060
                        }
                    ],
                    "estNextDivAmountNBT":0,
                    "estNextDivDate":1424736060,
                    "fundsActive":[
                        [
                            {
                                "ccedk_nbtppc":{
                                    "botBehavior":"Dual-side Custodian",
                                    "configuration":"https://kiaratamm.github.io/data/ccedk_nbtppc/options.json",
                                    "currentOrders":[
                                        {
                                            "exchangeAmount":0.0,
                                            "orderAmount":0.0,
                                            "orderCurrency":"",
                                            "orderType":"BUY",
                                            "paymentCurrency":"",
                                            "price":0
                                        },
                                        {
                                            "exchangeAmount":82884.796554,
                                            "orderAmount":31634.6122,
                                            "orderCurrency":"NBT",
                                            "orderType":"SELL",
                                            "paymentCurrency":"PPC",
                                            "price":2.62006678
                                        }
                                    ],
                                    "frozen":[],
                                    "liquidityAddress":"B7mmVdVQ1SNNcT9zuQRK1B3Cbvo8vHeoB1",
                                    "nonOrderBalance":[],
                                    "orderDataFile":"https://kiaratamm.github.io/data/ccedk_nbtppc/orders_history.json",
                                    "pairURL":"https://www.ccedk.com/nbt-ppc",
                                    "trades":{
                                        "day":{
                                            "buy":{
                                                "avgOrderSize":619.843749,
                                                "avgPrice":2.476483,
                                                "commission":0.002,
                                                "highPrice":2.529772,
                                                "lastTradeTime":1422423678000,
                                                "lowPrice":2.415699,
                                                "orders":9,
                                                "sumFees":11.157187,
                                                "sumSales":5578.593743
                                            },
                                            "filePath":"https://kiaratamm.github.io/data/ccedk_nbtppc/trades_lastday.json",
                                            "sell":{
                                                "avgOrderSize":798.237523,
                                                "avgPrice":2.500362,
                                                "commission":0.002,
                                                "highPrice":2.500362,
                                                "lastTradeTime":1422418937000,
                                                "lowPrice":2.500362,
                                                "orders":1,
                                                "sumFees":1.596475,
                                                "sumSales":798.237523
                                            }
                                        },
                                        "lifetime":{
                                            "buy":{
                                                "avgOrderSize":4247.557553,
                                                "avgPrice":1.755278,
                                                "commission":0.002,
                                                "highPrice":4.004073,
                                                "lastTradeTime":1422423678000,
                                                "lowPrice":0.002113,
                                                "orders":1438,
                                                "sumFees":12215.975515,
                                                "sumSales":6107987.761425
                                            },
                                            "filePath":"https://kiaratamm.github.io/data/ccedk_nbtppc/trades_alltime.json",
                                            "sell":{
                                                "avgOrderSize":3440.850767,
                                                "avgPrice":1.631096,
                                                "commission":0.002,
                                                "highPrice":4.03806,
                                                "lastTradeTime":1422418937000,
                                                "lowPrice":0.002143,
                                                "orders":1840,
                                                "sumFees":12663.307993,
                                                "sumSales":6331165.411925
                                            }
                                        },
                                        "thirty":{
                                            "buy":{
                                                "avgOrderSize":5288.780389,
                                                "avgPrice":2.186163,
                                                "commission":0.002,
                                                "highPrice":4.004073,
                                                "lastTradeTime":1422423678000,
                                                "lowPrice":1.703072,
                                                "orders":755,
                                                "sumFees":7986.058383,
                                                "sumSales":3993029.193924
                                            },
                                            "filePath":"https://kiaratamm.github.io/data/ccedk_nbtppc/trades_last30days.json",
                                            "sell":{
                                                "avgOrderSize":4101.627813,
                                                "avgPrice":2.096906,
                                                "commission":0.002,
                                                "highPrice":4.03806,
                                                "lastTradeTime":1422418937000,
                                                "lowPrice":1.698305,
                                                "orders":977,
                                                "sumFees":8014.580025,
                                                "sumSales":4007290.373634
                                            }
                                        },
                                        "week":{
                                            "buy":{
                                                "avgOrderSize":2025.138867,
                                                "avgPrice":2.459511,
                                                "commission":0.002,
                                                "highPrice":3.055415,
                                                "lastTradeTime":1422423678000,
                                                "lowPrice":1.978108,
                                                "orders":67,
                                                "sumFees":271.368608,
                                                "sumSales":135684.304075
                                            },
                                            "filePath":"https://kiaratamm.github.io/data/ccedk_nbtppc/trades_lastweek.json",
                                            "sell":{
                                                "avgOrderSize":2400.178882,
                                                "avgPrice":2.438251,
                                                "commission":0.002,
                                                "highPrice":3.146906,
                                                "lastTradeTime":1422418937000,
                                                "lowPrice":1.95157,
                                                "orders":49,
                                                "sumFees":235.21753,
                                                "sumSales":117608.765222
                                            }
                                        }
                                    },
                                    "wallDataFile":"https://kiaratamm.github.io/data/ccedk_nbtppc/wall_shifts.json",
                                    "wallshifts":{
                                        "buyPrice":2.60960743,
                                        "crypto":"PPC",
                                        "currency":"USD",
                                        "otherFeeds":"{\"price\":0.384101",
                                        "price":0.382433,
                                        "sellPrice":2.62006678,
                                        "source":"coinmarketcap_ne"
                                    }
                                }
                            },
                            {
                                "ccedk_nbtbtc":{
                                    "botBehavior":"Dual-side Custodian",
                                    "configuration":"https://kiaratamm.github.io/data/ccedk_nbtbtc/options.json",
                                    "currentOrders":[
                                        {
                                            "exchangeAmount":37.77900764,
                                            "orderAmount":9677.9419,
                                            "orderCurrency":"NBT",
                                            "orderType":"BUY",
                                            "paymentCurrency":"BTC",
                                            "price":0.00390362
                                        },
                                        {
                                            "exchangeAmount":329.63370896,
                                            "orderAmount":84105.8945,
                                            "orderCurrency":"NBT",
                                            "orderType":"SELL",
                                            "paymentCurrency":"BTC",
                                            "price":0.00391927
                                        }
                                    ],
                                    "frozen":[],
                                    "liquidityAddress":"B7mmVdVQ1SNNcT9zuQRK1B3Cbvo8vHeoB1",
                                    "nonOrderBalance":[],
                                    "orderDataFile":"https://kiaratamm.github.io/data/ccedk_nbtbtc/orders_history.json",
                                    "pairURL":"https://www.ccedk.com/nbt-btc",
                                    "trades":{
                                        "day":{
                                            "buy":{
                                                "avgOrderSize":8507.00060214,
                                                "avgPrice":0.0038576,
                                                "commission":0.002,
                                                "highPrice":0.00393626,
                                                "lastTradeTime":1422459150000,
                                                "lowPrice":0.00378432,
                                                "orders":13,
                                                "sumFees":221.18201552,
                                                "sumSales":110591.00782778
                                            },
                                            "filePath":"https://kiaratamm.github.io/data/ccedk_nbtbtc/trades_lastday.json",
                                            "sell":{
                                                "avgOrderSize":13362.32368717,
                                                "avgPrice":0.0038396,
                                                "commission":0.002,
                                                "highPrice":0.00395204,
                                                "lastTradeTime":1422454204000,
                                                "lowPrice":0.00377757,
                                                "orders":7,
                                                "sumFees":187.07251637,
                                                "sumSales":93536.26581019
                                            }
                                        },
                                        "lifetime":{
                                            "buy":{
                                                "avgOrderSize":8428.92895366,
                                                "avgPrice":0.00320687,
                                                "commission":0.002,
                                                "highPrice":0.00568086,
                                                "lastTradeTime":1422459150000,
                                                "lowPrice":0.00211323,
                                                "orders":1174,
                                                "sumFees":19791.12517622,
                                                "sumSales":9895562.59159751
                                            },
                                            "filePath":"https://kiaratamm.github.io/data/ccedk_nbtbtc/trades_alltime.json",
                                            "sell":{
                                                "avgOrderSize":8196.1218769,
                                                "avgPrice":0.00317122,
                                                "commission":0.002,
                                                "highPrice":0.00572255,
                                                "lastTradeTime":1422454204000,
                                                "lowPrice":0.00214303,
                                                "orders":1222,
                                                "sumFees":20031.31924651,
                                                "sumSales":10015660.93357155
                                            }
                                        },
                                        "thirty":{
                                            "buy":{
                                                "avgOrderSize":11057.45142,
                                                "avgPrice":0.00387124,
                                                "commission":0.002,
                                                "highPrice":0.00568086,
                                                "lastTradeTime":1422459150000,
                                                "lowPrice":0.00311846,
                                                "orders":433,
                                                "sumFees":9575.7529269,
                                                "sumSales":4787876.46485914
                                            },
                                            "filePath":"https://kiaratamm.github.io/data/ccedk_nbtbtc/trades_last30days.json",
                                            "sell":{
                                                "avgOrderSize":11431.21555996,
                                                "avgPrice":0.00378725,
                                                "commission":0.002,
                                                "highPrice":0.00572255,
                                                "lastTradeTime":1422454204000,
                                                "lowPrice":0.00313979,
                                                "orders":424,
                                                "sumFees":9693.67005034,
                                                "sumSales":4846835.39742357
                                            }
                                        },
                                        "week":{
                                            "buy":{
                                                "avgOrderSize":3280.15465423,
                                                "avgPrice":0.00389016,
                                                "commission":0.002,
                                                "highPrice":0.00438551,
                                                "lastTradeTime":1422459150000,
                                                "lowPrice":0.00327143,
                                                "orders":65,
                                                "sumFees":426.4201047,
                                                "sumSales":213210.05252491
                                            },
                                            "filePath":"https://kiaratamm.github.io/data/ccedk_nbtbtc/trades_lastweek.json",
                                            "sell":{
                                                "avgOrderSize":5340.01493001,
                                                "avgPrice":0.00383739,
                                                "commission":0.002,
                                                "highPrice":0.004589,
                                                "lastTradeTime":1422454204000,
                                                "lowPrice":0.00326242,
                                                "orders":36,
                                                "sumFees":384.48100209,
                                                "sumSales":192240.53748033
                                            }
                                        }
                                    },
                                    "wallDataFile":"https://kiaratamm.github.io/data/ccedk_nbtbtc/wall_shifts.json",
                                    "wallshifts":{
                                        "buyPrice":0.00390362,
                                        "crypto":"BTC",
                                        "currency":"USD",
                                        "otherFeeds":"{\"price\":255.0",
                                        "price":255.66,
                                        "sellPrice":0.00391927,
                                        "source":"bitcoinaverage"
                                    }
                                }
                            },
                            {
                                "ccedk_nbtusd":{
                                    "botBehavior":"Dual-side Custodian",
                                    "configuration":"https://kiaratamm.github.io/data/ccedk_nbtusd/options.json",
                                    "currentOrders":[
                                        {
                                            "exchangeAmount":0.0,
                                            "orderAmount":0.0,
                                            "orderCurrency":"",
                                            "orderType":"BUY",
                                            "paymentCurrency":"",
                                            "price":0
                                        },
                                        {
                                            "exchangeAmount":34057.0592,
                                            "orderAmount":33989.081,
                                            "orderCurrency":"NBT",
                                            "orderType":"SELL",
                                            "paymentCurrency":"USD",
                                            "price":1.002
                                        }
                                    ],
                                    "frozen":[],
                                    "liquidityAddress":"B7mmVdVQ1SNNcT9zuQRK1B3Cbvo8vHeoB1",
                                    "nonOrderBalance":[],
                                    "orderDataFile":"https://kiaratamm.github.io/data/ccedk_nbtusd/orders_history.json",
                                    "pairURL":"https://www.ccedk.com/nbt-usd",
                                    "trades":{
                                        "day":{
                                            "buy":{
                                                "avgOrderSize":0.0,
                                                "avgPrice":0.0,
                                                "commission":0,
                                                "highPrice":0.0,
                                                "lastTradeTime":0,
                                                "lowPrice":0.0,
                                                "orders":0,
                                                "sumFees":0.0,
                                                "sumSales":0.0
                                            },
                                            "filePath":"https://kiaratamm.github.io/data/ccedk_nbtusd/trades_lastday.json",
                                            "sell":{
                                                "avgOrderSize":0.0,
                                                "avgPrice":0.0,
                                                "commission":0,
                                                "highPrice":0.0,
                                                "lastTradeTime":0,
                                                "lowPrice":0.0,
                                                "orders":0,
                                                "sumFees":0.0,
                                                "sumSales":0.0
                                            }
                                        },
                                        "lifetime":{
                                            "buy":{
                                                "avgOrderSize":527.8899,
                                                "avgPrice":0.998,
                                                "commission":0.002,
                                                "highPrice":0.998,
                                                "lastTradeTime":1422194548000,
                                                "lowPrice":0.998,
                                                "orders":45,
                                                "sumFees":47.5101,
                                                "sumSales":23755.0433
                                            },
                                            "filePath":"https://kiaratamm.github.io/data/ccedk_nbtusd/trades_alltime.json",
                                            "sell":{
                                                "avgOrderSize":697.3074,
                                                "avgPrice":1.002,
                                                "commission":0.002,
                                                "highPrice":1.002,
                                                "lastTradeTime":1422124930000,
                                                "lowPrice":1.002,
                                                "orders":34,
                                                "sumFees":47.4169,
                                                "sumSales":23708.4522
                                            }
                                        },
                                        "thirty":{
                                            "buy":{
                                                "avgOrderSize":103.644,
                                                "avgPrice":0.998,
                                                "commission":0.002,
                                                "highPrice":0.998,
                                                "lastTradeTime":1422194548000,
                                                "lowPrice":0.998,
                                                "orders":18,
                                                "sumFees":3.7312,
                                                "sumSales":1865.5916
                                            },
                                            "filePath":"https://kiaratamm.github.io/data/ccedk_nbtusd/trades_last30days.json",
                                            "sell":{
                                                "avgOrderSize":252.1489,
                                                "avgPrice":1.002,
                                                "commission":0.002,
                                                "highPrice":1.002,
                                                "lastTradeTime":1422124930000,
                                                "lowPrice":1.002,
                                                "orders":7,
                                                "sumFees":3.5301,
                                                "sumSales":1765.0423
                                            }
                                        },
                                        "week":{
                                            "buy":{
                                                "avgOrderSize":134.8349,
                                                "avgPrice":0.998,
                                                "commission":0.002,
                                                "highPrice":0.998,
                                                "lastTradeTime":1422194548000,
                                                "lowPrice":0.998,
                                                "orders":5,
                                                "sumFees":1.3483,
                                                "sumSales":674.1743
                                            },
                                            "filePath":"https://kiaratamm.github.io/data/ccedk_nbtusd/trades_lastweek.json",
                                            "sell":{
                                                "avgOrderSize":673.6527,
                                                "avgPrice":1.002,
                                                "commission":0.002,
                                                "highPrice":1.002,
                                                "lastTradeTime":1422124930000,
                                                "lowPrice":1.002,
                                                "orders":1,
                                                "sumFees":1.3473,
                                                "sumSales":673.6527
                                            }
                                        }
                                    },
                                    "wallDataFile":"https://kiaratamm.github.io/data/ccedk_nbtusd/wall_shifts.json",
                                    "wallshifts":{
                                        "buyPrice":0,
                                        "crypto":"",
                                        "currency":"",
                                        "otherFeeds":"",
                                        "price":0,
                                        "sellPrice":0,
                                        "source":""
                                    }
                                }
                            },
                            {
                                "ccedk_nbteur":{
                                    "botBehavior":"Dual-side Custodian",
                                    "configuration":"https://kiaratamm.github.io/data/ccedk_nbteur/options.json",
                                    "currentOrders":[
                                        {
                                            "exchangeAmount":10728.3504,
                                            "orderAmount":12226.8796,
                                            "orderCurrency":"NBT",
                                            "orderType":"BUY",
                                            "paymentCurrency":"EUR",
                                            "price":0.87743977
                                        },
                                        {
                                            "exchangeAmount":32295.3995,
                                            "orderAmount":36659.4684,
                                            "orderCurrency":"NBT",
                                            "orderType":"SELL",
                                            "paymentCurrency":"EUR",
                                            "price":0.88095657
                                        }
                                    ],
                                    "frozen":[],
                                    "liquidityAddress":"B7mmVdVQ1SNNcT9zuQRK1B3Cbvo8vHeoB1",
                                    "nonOrderBalance":[],
                                    "orderDataFile":"https://kiaratamm.github.io/data/ccedk_nbteur/orders_history.json",
                                    "pairURL":"https://www.ccedk.com/nbt-eur",
                                    "trades":{
                                        "day":{
                                            "buy":{
                                                "avgOrderSize":0.0,
                                                "avgPrice":0.0,
                                                "commission":0,
                                                "highPrice":0.0,
                                                "lastTradeTime":0,
                                                "lowPrice":0.0,
                                                "orders":0,
                                                "sumFees":0.0,
                                                "sumSales":0.0
                                            },
                                            "filePath":"https://kiaratamm.github.io/data/ccedk_nbteur/trades_lastday.json",
                                            "sell":{
                                                "avgOrderSize":0.4187,
                                                "avgPrice":0.881,
                                                "commission":0.002,
                                                "highPrice":0.881,
                                                "lastTradeTime":1422454040000,
                                                "lowPrice":0.881,
                                                "orders":2,
                                                "sumFees":0.0017,
                                                "sumSales":0.8373
                                            }
                                        },
                                        "lifetime":{
                                            "buy":{
                                                "avgOrderSize":901.9705,
                                                "avgPrice":0.8314,
                                                "commission":0.002,
                                                "highPrice":0.8906,
                                                "lastTradeTime":1422358306000,
                                                "lowPrice":0.7843,
                                                "orders":34,
                                                "sumFees":61.334,
                                                "sumSales":30666.9959
                                            },
                                            "filePath":"https://kiaratamm.github.io/data/ccedk_nbteur/trades_alltime.json",
                                            "sell":{
                                                "avgOrderSize":549.3274,
                                                "avgPrice":0.8139,
                                                "commission":0.002,
                                                "highPrice":0.8942,
                                                "lastTradeTime":1422454040000,
                                                "lowPrice":0.7843,
                                                "orders":80,
                                                "sumFees":87.8924,
                                                "sumSales":43946.1936
                                            }
                                        },
                                        "thirty":{
                                            "buy":{
                                                "avgOrderSize":1051.3504,
                                                "avgPrice":0.8549,
                                                "commission":0.002,
                                                "highPrice":0.8906,
                                                "lastTradeTime":1422358306000,
                                                "lowPrice":0.8057,
                                                "orders":19,
                                                "sumFees":39.9513,
                                                "sumSales":19975.6577
                                            },
                                            "filePath":"https://kiaratamm.github.io/data/ccedk_nbteur/trades_last30days.json",
                                            "sell":{
                                                "avgOrderSize":767.135,
                                                "avgPrice":0.8562,
                                                "commission":0.002,
                                                "highPrice":0.8942,
                                                "lastTradeTime":1422454040000,
                                                "lowPrice":0.809,
                                                "orders":19,
                                                "sumFees":29.1511,
                                                "sumSales":14575.5643
                                            }
                                        },
                                        "week":{
                                            "buy":{
                                                "avgOrderSize":1518.1985,
                                                "avgPrice":0.8654,
                                                "commission":0.002,
                                                "highPrice":0.8906,
                                                "lastTradeTime":1422358306000,
                                                "lowPrice":0.8474,
                                                "orders":12,
                                                "sumFees":36.4368,
                                                "sumSales":18218.3823
                                            },
                                            "filePath":"https://kiaratamm.github.io/data/ccedk_nbteur/trades_lastweek.json",
                                            "sell":{
                                                "avgOrderSize":1567.5955,
                                                "avgPrice":0.8824,
                                                "commission":0.002,
                                                "highPrice":0.8942,
                                                "lastTradeTime":1422454040000,
                                                "lowPrice":0.8508,
                                                "orders":8,
                                                "sumFees":25.0815,
                                                "sumSales":12540.7636
                                            }
                                        }
                                    },
                                    "wallDataFile":"https://kiaratamm.github.io/data/ccedk_nbteur/wall_shifts.json",
                                    "wallshifts":{
                                        "buyPrice":0,
                                        "crypto":"",
                                        "currency":"",
                                        "otherFeeds":"",
                                        "price":0,
                                        "sellPrice":0,
                                        "source":""
                                    }
                                }
                            },
                            {
                                "excoin_btcnbt":{
                                    "botBehavior":"Liquidity Providing Custodian",
                                    "configuration":"https://kiaratamm.github.io/data/excoin_btcnbt/options.json",
                                    "currentOrders":[
                                        {
                                            "exchangeAmount":0,
                                            "orderAmount":0,
                                            "orderCurrency":"",
                                            "orderType":"BUY",
                                            "paymentCurrency":"",
                                            "price":0
                                        },
                                        {
                                            "exchangeAmount":0,
                                            "orderAmount":0,
                                            "orderCurrency":"",
                                            "orderType":"SELL",
                                            "paymentCurrency":"",
                                            "price":0
                                        }
                                    ],
                                    "frozen":[],
                                    "liquidityAddress":"",
                                    "nonOrderBalance":[
                                        {
                                            "amount":39.04287034,
                                            "currency":"btc",
                                            "notes":"Exchange wall balance fund"
                                        },
                                        {
                                            "amount":62986.33034668,
                                            "currency":"nbt",
                                            "notes":"Exchange wall balance fund"
                                        }
                                    ],
                                    "orderDataFile":"https://kiaratamm.github.io/data/excoin_btcnbt/orders_history.json",
                                    "pairURL":"https://exco.in/exchange/NBT/BTC",
                                    "trades":{
                                        "day":{
                                            "buy":{
                                                "avgOrderSize":0.0,
                                                "avgPrice":0.0,
                                                "commission":0,
                                                "highPrice":0.0,
                                                "lastTradeTime":0,
                                                "lowPrice":0.0,
                                                "orders":0,
                                                "sumFees":0.0,
                                                "sumSales":0.0
                                            },
                                            "filePath":"https://kiaratamm.github.io/data/excoin_btcnbt/trades_lastday.json",
                                            "sell":{
                                                "avgOrderSize":0.0,
                                                "avgPrice":0.0,
                                                "commission":0,
                                                "highPrice":0.0,
                                                "lastTradeTime":0,
                                                "lowPrice":0.0,
                                                "orders":0,
                                                "sumFees":0.0,
                                                "sumSales":0.0
                                            }
                                        },
                                        "lifetime":{
                                            "buy":{
                                                "avgOrderSize":4463.033,
                                                "avgPrice":270.0008,
                                                "commission":0.002,
                                                "highPrice":289.8435,
                                                "lastTradeTime":1421181589242,
                                                "lowPrice":235.1382,
                                                "orders":11,
                                                "sumFees":73.64,
                                                "sumSales":49093.3625
                                            },
                                            "filePath":"https://kiaratamm.github.io/data/excoin_btcnbt/trades_alltime.json",
                                            "sell":{
                                                "avgOrderSize":4126.1551,
                                                "avgPrice":269.8524,
                                                "commission":0.001,
                                                "highPrice":289.7565,
                                                "lastTradeTime":1421268486908,
                                                "lowPrice":197.8842,
                                                "orders":9,
                                                "sumFees":55.7031,
                                                "sumSales":37135.3959
                                            }
                                        },
                                        "thirty":{
                                            "buy":{
                                                "avgOrderSize":4463.033,
                                                "avgPrice":270.0008,
                                                "commission":0.002,
                                                "highPrice":289.8435,
                                                "lastTradeTime":1421181589242,
                                                "lowPrice":235.1382,
                                                "orders":11,
                                                "sumFees":73.64,
                                                "sumSales":49093.3625
                                            },
                                            "filePath":"https://kiaratamm.github.io/data/excoin_btcnbt/trades_last30days.json",
                                            "sell":{
                                                "avgOrderSize":4126.1551,
                                                "avgPrice":269.8524,
                                                "commission":0.001,
                                                "highPrice":289.7565,
                                                "lastTradeTime":1421268486908,
                                                "lowPrice":197.8842,
                                                "orders":9,
                                                "sumFees":55.7031,
                                                "sumSales":37135.3959
                                            }
                                        },
                                        "week":{
                                            "buy":{
                                                "avgOrderSize":0.0,
                                                "avgPrice":0.0,
                                                "commission":0,
                                                "highPrice":0.0,
                                                "lastTradeTime":0,
                                                "lowPrice":0.0,
                                                "orders":0,
                                                "sumFees":0.0,
                                                "sumSales":0.0
                                            },
                                            "filePath":"https://kiaratamm.github.io/data/excoin_btcnbt/trades_lastweek.json",
                                            "sell":{
                                                "avgOrderSize":0.0,
                                                "avgPrice":0.0,
                                                "commission":0,
                                                "highPrice":0.0,
                                                "lastTradeTime":0,
                                                "lowPrice":0.0,
                                                "orders":0,
                                                "sumFees":0.0,
                                                "sumSales":0.0
                                            }
                                        }
                                    },
                                    "wallDataFile":"https://kiaratamm.github.io/data/excoin_btcnbt/wall_shifts.json",
                                    "wallshifts":{
                                        "buyPrice":0,
                                        "crypto":"",
                                        "currency":"",
                                        "otherFeeds":"",
                                        "price":0,
                                        "sellPrice":0,
                                        "source":""
                                    }
                                }
                            }
                        ]
                    ],
                    "fundsReserve":[
                        {
                            "address":"BSyDq6yQ3vt2URGcBhJRmAdsNuQ5pXkAsx",
                            "amount":237630.3948,
                            "currency":"nbt",
                            "notes":"Now that coin control has been included, I moved the grant's reserve funds to unique addresses. It will be easier to keep track of incoming and outgoing transactions. This also allows me to split the reserve into multiple blocks for enhanced security.",
                            "source":"Grant Reserve Address #1"
                        },
                        {
                            "address":"BHkpxLHvfkA7dqZLNkN7MWVyCatKQ9wThY",
                            "amount":237630.3948,
                            "currency":"nbt",
                            "notes":"",
                            "source":"Grant Reserve Address #2"
                        },
                        {
                            "address":"BB4BUgf8PqfcG6tryUATV3QiLdwyejaQcZ",
                            "amount":237630.3948,
                            "currency":"nbt",
                            "notes":"",
                            "source":"Grant Reserve Address #3"
                        },
                        {
                            "address":"BCCB8roJPNCNGzkzC5hasVGVAYtKB9i9C4",
                            "amount":237630.3948,
                            "currency":"nbt",
                            "notes":"",
                            "source":"Grant Reserve Address #4"
                        },
                        {
                            "address":"BBoyA8PdVNHCzWRXJcudqYf3SQATgHDcMi",
                            "amount":237630.3648,
                            "currency":"nbt",
                            "notes":"",
                            "source":"Grant Reserve Address #5"
                        }
                    ],
                    "futureDividendWitheld":[
                        {
                            "address":"",
                            "amount":0,
                            "currency":""
                        }
                    ],
                    "grantAddress":"B7mmVdVQ1SNNcT9zuQRK1B3Cbvo8vHeoB1",
                    "grantAmount":1836450,
                    "grantTXID":"65394263c260e75b5f9fb0a8bbe95f71f8bd752bdc8e9a1ea21179c3e91f64d5",
                    "proposalURL":"https://gist.github.com/KiaraTamm/c30172f9d5d73e970bf2",
                    "shareholderApprovalInNuBlock":15459,
                    "status":"active",
                    "type":"dual-side"
                }
            ],
            "profileName":"KTm",
            "profilePath":"https://discuss.nubits.com/users/ktm"
        }
    ],
    "reportGenerated":1422465098101,
    "reportRepository":"https://kiaratamm.github.io/"
}