{

"Trade_84758":{
"id":"84758",
"order_id":"null",
"exchange":"ccedk",
"pair":"nbteur",
"type":"SELL",
"price":0.89011963,
"amount":0.96136934,
"fee":0.00171145,
"timestamp":1423681361000
},

"Trade_84634":{
"id":"84634",
"order_id":"null",
"exchange":"ccedk",
"pair":"nbteur",
"type":"SELL",
"price":0.89011963,
"amount":7.93735618,
"fee":0.01413038,
"timestamp":1423677776000
},

"Trade_84502":{
"id":"84502",
"order_id":"null",
"exchange":"ccedk",
"pair":"nbteur",
"type":"SELL",
"price":0.88775961,
"amount":5.39740708,
"fee":0.00958318,
"timestamp":1423674321000
},

"Trade_83876":{
"id":"83876",
"order_id":"null",
"exchange":"ccedk",
"pair":"nbteur",
"type":"SELL",
"price":0.88666255,
"amount":1829.3318016,
"fee":3.24399999,
"timestamp":1423641536000
},

"Trade_82693":{
"id":"82693",
"order_id":"null",
"exchange":"ccedk",
"pair":"nbteur",
"type":"BUY",
"price":0.87856323,
"amount":0.04575425,
"fee":0.0000915,
"timestamp":1423551828000
},

"Trade_82311":{
"id":"82311",
"order_id":"null",
"exchange":"ccedk",
"pair":"nbteur",
"type":"BUY",
"price":0.87918396,
"amount":198.68781972,
"fee":0.39737562,
"timestamp":1423522420000
},

"Trade_81742":{
"id":"81742",
"order_id":"null",
"exchange":"ccedk",
"pair":"nbteur",
"type":"SELL",
"price":0.88713239,
"amount":618.84788132,
"fee":1.09799999,
"timestamp":1423485994000
},

"Trade_81612":{
"id":"81612",
"order_id":"null",
"exchange":"ccedk",
"pair":"nbteur",
"type":"SELL",
"price":0.88713239,
"amount":881.68241157,
"fee":1.56433804,
"timestamp":1423477510000
},

"Trade_81610":{
"id":"81610",
"order_id":"null",
"exchange":"ccedk",
"pair":"nbteur",
"type":"SELL",
"price":0.88713239,
"amount":2500.0,
"fee":4.43566195,
"timestamp":1423477510000
},

"Trade_80633":{
"id":"80633",
"order_id":"null",
"exchange":"ccedk",
"pair":"nbteur",
"type":"BUY",
"price":0.87980557,
"amount":0.43092069,
"fee":0.00086184,
"timestamp":1423418624000
},

"Trade_78369":{
"id":"78369",
"order_id":"null",
"exchange":"ccedk",
"pair":"nbteur",
"type":"BUY",
"price":0.87980557,
"amount":0.03632507,
"fee":0.00007264,
"timestamp":1423321402000
},

"Trade_78241":{
"id":"78241",
"order_id":"null",
"exchange":"ccedk",
"pair":"nbteur",
"type":"BUY",
"price":0.87980557,
"amount":0.03053362,
"fee":0.00006106,
"timestamp":1423317860000
},

"Trade_74708":{
"id":"74708",
"order_id":"null",
"exchange":"ccedk",
"pair":"nbteur",
"type":"SELL",
"price":0.87759916,
"amount":64.95231832,
"fee":0.11400418,
"timestamp":1423160788000
},

"Trade_74706":{
"id":"74706",
"order_id":"null",
"exchange":"ccedk",
"pair":"nbteur",
"type":"SELL",
"price":0.87759916,
"amount":2500.0,
"fee":4.3879958,
"timestamp":1423160783000
},

"Trade_74656":{
"id":"74656",
"order_id":"null",
"exchange":"ccedk",
"pair":"nbteur",
"type":"SELL",
"price":0.87759916,
"amount":0.08775419,
"fee":0.00015401,
"timestamp":1423155809000
},

"Trade_74591":{
"id":"74591",
"order_id":"null",
"exchange":"ccedk",
"pair":"nbteur",
"type":"BUY",
"price":0.86973615,
"amount":1.31510945,
"fee":0.0026302,
"timestamp":1423152146000
}
}
